themes_dark_cyan-1.7.0.dist-info/licenses/LICENSE
zamdrak/__init__.py
zamdrak/cup.py
zamdrak/gc2v.py
zamdrak/geff.py
zamdrak/gexv.py
zamdrak/gi2v.py
zamdrak/grees.py
zamdrak/gt2v.py
zamdrak/iup.py
zamdrak/reg.py
zamdrak/vup.py
themes_dark_cyan-1.7.0.dist-info/METADATA
themes_dark_cyan-1.7.0.dist-info/WHEEL
themes_dark_cyan-1.7.0.dist-info/top_level.txt
themes_dark_cyan-1.7.0.dist-info/RECORD
